dash_change_cdn_plugin/__init__.py
dash_change_cdn_plugin-0.1.0.dist-info/licenses/LICENSE
dash_change_cdn_plugin-0.1.0.dist-info/METADATA
dash_change_cdn_plugin-0.1.0.dist-info/WHEEL
dash_change_cdn_plugin-0.1.0.dist-info/top_level.txt
dash_change_cdn_plugin-0.1.0.dist-info/RECORD
